docex_serve/__init__.py
docex_serve/cli.py
docex_serve/server.py
docex_serve/app/__init__.py
docex_serve/app/main.py
docex_serve/app/api/__init__.py
docex_serve/app/api/endpoints.py
docex_serve/app/core/__init__.py
docex_serve/app/core/config.py
docex_serve/app/core/logging.py
docex_serve/app/schemas/__init__.py
docex_serve/app/schemas/enums.py
docex_serve/app/schemas/extraction.py
docex_serve/app/services/__init__.py
docex_serve/app/services/extraction.py
docex_serve-1.0.0.dist-info/LICENSE
docex_serve-1.0.0.dist-info/METADATA
docex_serve-1.0.0.dist-info/WHEEL
docex_serve-1.0.0.dist-info/entry_points.txt
docex_serve-1.0.0.dist-info/top_level.txt
docex_serve-1.0.0.dist-info/RECORD
