Metadata-Version: 2.1
Name: docex-serve
Version: 1.0.0
Summary: Document extraction API with multi-provider VLM support
Home-page: https://github.com/ryyhan/docEx
Author: ryyhan
Author-email: ryyhan <dayel.rehan@gmail.com>
License: MIT
Project-URL: Homepage, https://github.com/ryyhan/docEx
Project-URL: Documentation, https://github.com/ryyhan/docEx#readme
Project-URL: Repository, https://github.com/ryyhan/docEx
Project-URL: Issues, https://github.com/ryyhan/docEx/issues
Keywords: document,extraction,pdf,vlm,ocr,fastapi,docling
Classifier: Development Status :: 4 - Beta
Classifier: Intended Audience :: Developers
Classifier: License :: OSI Approved :: MIT License
Classifier: Programming Language :: Python :: 3
Classifier: Programming Language :: Python :: 3.10
Classifier: Programming Language :: Python :: 3.11
Classifier: Programming Language :: Python :: 3.12
Requires-Python: >=3.10
License-File: LICENSE
Provides-Extra: dev
Requires-Dist: pytest>=8.3.0; extra == "dev"
Requires-Dist: httpx>=0.27.0; extra == "dev"
